CHANGES.rst
MANIFEST.in
README.rst
setup.cfg
setup.py
clictagger/__init__.py
clictagger/icuconfig.py
clictagger/markup.py
clictagger/script.py
clictagger/table.py
clictagger/taggedtext.py
clictagger/tokenizer.py
clictagger.egg-info/PKG-INFO
clictagger.egg-info/SOURCES.txt
clictagger.egg-info/dependency_links.txt
clictagger.egg-info/entry_points.txt
clictagger.egg-info/requires.txt
clictagger.egg-info/top_level.txt
clictagger/region/__init__.py
clictagger/region/chapter.py
clictagger/region/metadata.py
clictagger/region/quote.py
clictagger/region/suspension.py
clictagger/region/tag.py
clictagger/region/utils.py
tests/__init__.py
tests/test_script.py
tests/test_tokenizer.py