Metadata-Version: 2.1
Name: clictagger
Version: 0.9.0
Summary: CLiC region tagging
Home-page: https://github.com/mahlberg-lab/clictagger
Author: Jamie Lentin
Author-email: jamie.lentin@shuttlethread.com
License: MIT
Platform: UNKNOWN
Classifier: License :: OSI Approved :: MIT License
Classifier: Programming Language :: Python :: 3
Requires-Python: >=3.6
Provides-Extra: testing
